main.py
source_hibob/__init__.py
source_hibob/manifest.yaml
source_hibob/run.py
source_hibob/source.py
airbyte_source_hibob-0.1.3.dist-info/METADATA
airbyte_source_hibob-0.1.3.dist-info/WHEEL
airbyte_source_hibob-0.1.3.dist-info/entry_points.txt
airbyte_source_hibob-0.1.3.dist-info/RECORD
